{
  "mini-css-extract-plugin node_modules/css-loader/index.js??ref--5-1!pages/css/reset.css": [
    {
      "modules": {
        "byIdentifier": {},
        "usedIds": {}
      },
      "chunks": {
        "byName": {
          "mini-css-extract-plugin": 0
        },
        "bySource": {},
        "usedIds": [
          0
        ]
      }
    }
  ],
  "mini-css-extract-plugin node_modules/css-loader/index.js??ref--5-1!pages/css/toggle.css": [
    {
      "modules": {
        "byIdentifier": {},
        "usedIds": {}
      },
      "chunks": {
        "byName": {
          "mini-css-extract-plugin": 0
        },
        "bySource": {},
        "usedIds": [
          0
        ]
      }
    }
  ],
  "mini-css-extract-plugin node_modules/css-loader/index.js??ref--5-1!pages/css/index.css": [
    {
      "modules": {
        "byIdentifier": {},
        "usedIds": {}
      },
      "chunks": {
        "byName": {
          "mini-css-extract-plugin": 0
        },
        "bySource": {},
        "usedIds": [
          0
        ]
      }
    }
  ],
  "mini-css-extract-plugin node_modules/css-loader/index.js??ref--5-1!pages/css/header.css": [
    {
      "modules": {
        "byIdentifier": {},
        "usedIds": {}
      },
      "chunks": {
        "byName": {
          "mini-css-extract-plugin": 0
        },
        "bySource": {},
        "usedIds": [
          0
        ]
      }
    }
  ],
  "mini-css-extract-plugin node_modules/css-loader/index.js??ref--5-1!pages/css/settings.css": [
    {
      "modules": {
        "byIdentifier": {},
        "usedIds": {}
      },
      "chunks": {
        "byName": {
          "mini-css-extract-plugin": 0
        },
        "bySource": {},
        "usedIds": [
          0
        ]
      }
    }
  ],
  "mini-css-extract-plugin node_modules/css-loader/index.js??ref--5-1!pages/css/menue.css": [
    {
      "modules": {
        "byIdentifier": {},
        "usedIds": {}
      },
      "chunks": {
        "byName": {
          "mini-css-extract-plugin": 0
        },
        "bySource": {},
        "usedIds": [
          0
        ]
      }
    }
  ],
  "mini-css-extract-plugin node_modules/css-loader/index.js??ref--5-1!node_modules/rc-slider/assets/index.css": [
    {
      "modules": {
        "byIdentifier": {},
        "usedIds": {}
      },
      "chunks": {
        "byName": {
          "mini-css-extract-plugin": 0
        },
        "bySource": {},
        "usedIds": [
          0
        ]
      }
    }
  ],
  "mini-css-extract-plugin node_modules/css-loader/index.js??ref--5-1!sled/index.css": [
    {
      "modules": {
        "byIdentifier": {},
        "usedIds": {}
      },
      "chunks": {
        "byName": {
          "mini-css-extract-plugin": 0
        },
        "bySource": {},
        "usedIds": [
          0
        ]
      }
    }
  ],
  "mini-css-extract-plugin node_modules/css-loader/index.js??ref--5-1!sled/control/index.css": [
    {
      "modules": {
        "byIdentifier": {},
        "usedIds": {}
      },
      "chunks": {
        "byName": {
          "mini-css-extract-plugin": 0
        },
        "bySource": {},
        "usedIds": [
          0
        ]
      }
    }
  ],
  "mini-css-extract-plugin node_modules/css-loader/index.js??ref--5-1!sled/progress/index.css": [
    {
      "modules": {
        "byIdentifier": {},
        "usedIds": {}
      },
      "chunks": {
        "byName": {
          "mini-css-extract-plugin": 0
        },
        "bySource": {},
        "usedIds": [
          0
        ]
      }
    }
  ],
  "modules": {
    "byIdentifier": {
      "css node_modules/css-loader/index.js??ref--5-1!pages/css/reset.css 0": 0,
      "css node_modules/css-loader/index.js??ref--5-1!pages/css/toggle.css 0": 1,
      "css node_modules/css-loader/index.js??ref--5-1!pages/css/index.css 0": 2,
      "css node_modules/css-loader/index.js??ref--5-1!pages/css/header.css 0": 3,
      "css node_modules/css-loader/index.js??ref--5-1!pages/css/settings.css 0": 4,
      "css node_modules/css-loader/index.js??ref--5-1!pages/css/menue.css 0": 5,
      "css node_modules/css-loader/index.js??ref--5-1!sled/index.css 0": 6,
      "css node_modules/css-loader/index.js??ref--5-1!sled/control/index.css 0": 7,
      "css node_modules/css-loader/index.js??ref--5-1!sled/progress/index.css 0": 8,
      "css node_modules/css-loader/index.js??ref--5-1!node_modules/rc-slider/assets/index.css 0": 9
    },
    "usedIds": {
      "0": 0,
      "1": 1,
      "2": 2,
      "3": 3,
      "4": 4,
      "5": 5,
      "6": 6,
      "7": 7,
      "8": 8,
      "9": 9
    }
  },
  "chunks": {
    "byName": {
      "commons": 0,
      "static/runtime/webpack.js": 1,
      "styles": 2,
      "static/BY6XrIMqv-sNKZDerdAAN/pages/_app.js": 3,
      "static/BY6XrIMqv-sNKZDerdAAN/pages/_error.js": 4,
      "static/BY6XrIMqv-sNKZDerdAAN/pages/custom.js": 5,
      "static/BY6XrIMqv-sNKZDerdAAN/pages/index.js": 6,
      "static/BY6XrIMqv-sNKZDerdAAN/pages/test-basic.js": 7,
      "static/BY6XrIMqv-sNKZDerdAAN/pages/test.js": 8,
      "static/runtime/main.js": 9,
      "static/runtime/polyfills.js": 10,
      "static/ihORWr0lNijUKvXrP8MxC/pages/_app.js": 11,
      "static/ihORWr0lNijUKvXrP8MxC/pages/_error.js": 12,
      "static/ihORWr0lNijUKvXrP8MxC/pages/custom.js": 13,
      "static/ihORWr0lNijUKvXrP8MxC/pages/index.js": 14,
      "static/ihORWr0lNijUKvXrP8MxC/pages/test-basic.js": 15,
      "static/ihORWr0lNijUKvXrP8MxC/pages/test.js": 16,
      "static/Mxxi5qflCpJAlEXwCxfyj/pages/_app.js": 3,
      "static/Mxxi5qflCpJAlEXwCxfyj/pages/_error.js": 4,
      "static/Mxxi5qflCpJAlEXwCxfyj/pages/custom.js": 5,
      "static/Mxxi5qflCpJAlEXwCxfyj/pages/index.js": 6,
      "static/Mxxi5qflCpJAlEXwCxfyj/pages/test-basic.js": 7,
      "static/Mxxi5qflCpJAlEXwCxfyj/pages/test.js": 8
    },
    "bySource": {},
    "usedIds": [
      0,
      1,
      10,
      2,
      3,
      4,
      5,
      6,
      7,
      8,
      9
    ]
  }
}